aioxiq/__init__.py
aioxiq/v2/__init__.py
aioxiq/v2/auth.py
aioxiq/v2/client.py
aioxiq/v2/devices.py
aioxiq/v2/locations.py
aioxiq/v2/xiq_client.py
aio_xiq-0.4.0.dist-info/WHEEL
aio_xiq-0.4.0.dist-info/METADATA
aio_xiq-0.4.0.dist-info/RECORD
