Metadata-Version: 2.1
Name: aio-xiq
Version: 0.4.0
Summary: AsyncIO client for Extreme Cloud IQ
Home-page: https://github.com/jeremyschulman/aio-xiq
License: Apache-2.0
Author: Jeremy Schulman
Author-email: jeremy.schulman@mlb.com
Requires-Python: >=3.8,<4.0
Classifier: License :: OSI Approved :: Apache Software License
Classifier: Programming Language :: Python :: 3
Classifier: Programming Language :: Python :: 3.10
Classifier: Programming Language :: Python :: 3.8
Classifier: Programming Language :: Python :: 3.9
Requires-Dist: httpx (>=0.18.1,<0.19.0)
Requires-Dist: tenacity (>=7.0.0,<8.0.0)
Project-URL: Repository, https://github.com/jeremyschulman/aio-xiq
